qnnpy-0.1.17.dist-info/METADATA
qnnpy-0.1.17.dist-info/WHEEL
qnnpy-0.1.17.dist-info/entry_points.txt
qnnpy-0.1.17.dist-info/licenses/LICENSE.txt
qnnpy/__init__.py
qnnpy/functions/ICE_plot.py
qnnpy/functions/__init__.py
qnnpy/functions/functions.py
qnnpy/functions/ic_sweep.py
qnnpy/functions/laserctrl.py
qnnpy/functions/laserctrl_cmd_based.py
qnnpy/functions/logging/__init__.py
qnnpy/functions/logging/free_space_cryo_logging.py
qnnpy/functions/logging/ice-log_pressure-reader.py
qnnpy/functions/logging/ice-log_pressure-reader.pyw
qnnpy/functions/logging/ice_logging.py
qnnpy/functions/logging/ice_logging_script.py
qnnpy/functions/logging/ice_logging_script.pyw
qnnpy/functions/logging/ice_logging_watchdog.pyw
qnnpy/functions/logging/janis_300mK_logging.py
qnnpy/functions/logging/janis_300mK_logging.pyw
qnnpy/functions/logging/probe_station_logging.py
qnnpy/functions/logging/probe_station_logging.pyw
qnnpy/functions/logging/run_logging.bat
qnnpy/functions/microwave.py
qnnpy/functions/ntron.py
qnnpy/functions/plotting.py
qnnpy/functions/resonators.py
qnnpy/functions/save_data_vs_param.py
qnnpy/functions/snspd.py
qnnpy/functions/tc_measurement.py
qnnpy/functions/tc_measurement_muxed.py
qnnpy/instruments/AQ4321D_tunable_laser.py
qnnpy/instruments/BK_4060_awg.py
qnnpy/instruments/N5224A.py
qnnpy/instruments/README.md
qnnpy/instruments/ThorlabsPM100_meta.py
qnnpy/instruments/__init__.py
qnnpy/instruments/agilent_33250a.py
qnnpy/instruments/agilent_33600a.py
qnnpy/instruments/agilent_53131a.py
qnnpy/instruments/agilent_53230a.py
qnnpy/instruments/agilent_8153a.py
qnnpy/instruments/agilent_e5061b.py
qnnpy/instruments/agilent_n9020a.py
qnnpy/instruments/anritsu_mg9638a.py
qnnpy/instruments/attocube_anc150.py
qnnpy/instruments/attocube_anc300.py
qnnpy/instruments/cryocon34.py
qnnpy/instruments/cryocon350.py
qnnpy/instruments/development_test.py
qnnpy/instruments/exfo_t100s.py
qnnpy/instruments/fva3100_optical_attenuator.py
qnnpy/instruments/hmc_t2240.py
qnnpy/instruments/hp_3478a.py
qnnpy/instruments/hp_8157a.py
qnnpy/instruments/hp_83711b.py
qnnpy/instruments/hp_8722c.py
qnnpy/instruments/jds_ha9.py
qnnpy-0.1.17.dist-info/RECORD
