Metadata-Version: 2.1
Name: qnnpy
Version: 0.1.17
Summary: The QNN library for instrument control
Keywords: nanowire_electronics,instrument control
Author-Email: "O. Medeiros" <omedeiro@mit.edu>, "E. Battson" <emmabat@mit.edu>, "A. Simon" <alejansi@mit.edu>, "R. Foster" <reedf@mit.edu>
Maintainer-Email: "O. Medeiros" <omedeiro@mit.edu>
License: Copyright (c) 2016 The Python Packaging Authority (PyPA)
Classifier: Programming Language :: Python :: 3
Classifier: License :: OSI Approved :: MIT License
Classifier: Operating System :: OS Independent
Classifier: Intended Audience :: Science/Research
Classifier: Topic :: Scientific/Engineering
Project-URL: Homepage, https://github.com/qnngroup/qnnpy
Project-URL: Issues, https://github.com/qnngroup/qnnpy/issues
Project-URL: Documentation, https://qnnpy.readthedocs.io/en/latest/
Requires-Python: >=3.8
Requires-Dist: numpy
Requires-Dist: pyyaml
Requires-Dist: pyvisa
Requires-Dist: mariadb
Requires-Dist: pandas
Requires-Dist: nptdms
Requires-Dist: scipy
Requires-Dist: matplotlib
